Workbook

Sheet Assumptions
A1: IMPRESSIONS SERVICES PRIVATE LIMITED
A2: PROJECTIONS FY 2026-27 — KEY ASSUMPTIONS
A3: CIN: U74930DL2002PTC114966 | Base: BS_TB 2025-26 CONSOLIDATED Set 2 | Amount in INR
A5: Driver / Item | B5: Basis | C5: Value
A6: Revenue from operations | B6: Growth over FY 2025-26 | C6: 0.1
A7: Purchases of stock-in-trade | B7: Proportionate to sales (+10%) | C7: 0.1
A8: Employee benefits expense | B8: Proportionate to sales (+10%) — manpower-linked business | C8: 0.1
A9: Finance cost | B9: Grown +10% (prudence: working capital rises with sales) | C9: 0.1
A10: Depreciation | B10: Grown +10% (maintenance capex assumed ≈ depreciation) | C10: 0.1
A11: Other expenses | B11: Proportionate to sales (+10%) | C11: 0.1
A12: Other income | B12: PRUDENCE: held flat at FY26 level — not grown | C12: 0
A13: Change in inventories | B13: PRUDENCE: taken as NIL — no stock gain assumed
A14: Current tax | B14: PRUDENCE: full provision @ 25.168% (s.115BAA); no prior-year tax credits assumed | C14: 0.25168
A15: Dividend | B15: PRUDENCE: nil — entire PAT retained in reserves
A16: Trade receivables / inventories / ST loans & adv / other CA | B16: Scale with sales (+10%) — same collection cycle assumed | C16: 0.1
A17: Trade payables / other current liabilities / ST provisions | B17: Scale with sales (+10%) | C17: 0.1
A18: Long-term provisions (gratuity) | B18: Scale with employee cost (+10%) | C18: 0.1
A19: Long & short-term borrowings | B19: PRUDENCE: held at FY26 level — growth funded internally | C19: 0
A20: Share capital / investments / DTA / LT loans & advances / interunit | B20: Held constant | C20: 0
A21: Property, plant & equipment (net) | B21: Held flat — capex assumed equal to depreciation | C21: 0
A22: Cash & cash equivalents | B22: Balancing figure
A24: Note: Change the growth rate in cell C6 — the projected P&L and Balance Sheet recalculate automatically.

Sheet Projected P&L FY27
A1: IMPRESSIONS SERVICES PRIVATE LIMITED
A2: PROJECTED STATEMENT OF PROFIT AND LOSS FOR THE YEAR ENDING MARCH 31, 2027
A3: CIN: U74930DL2002PTC114966 | Base: BS_TB 2025-26 CONSOLIDATED Set 2 | Amount in INR
B5: Particulars | C5: FY 2025-26 (Base) | D5: FY 2026-27 (Projected) | E5: Change | F5: Basis
A6: I | B6: Revenue from Operations | C6: 4.8982381e+09 | D6: =C6*(1+Assumptions!$C$6) | E6: =IFERROR(D6/C6-1,"") | F6: Sales +10%
A7: II | B7: Other income | C7: 9993615.7 | D7: =C7 | E7: =IFERROR(D7/C7-1,"") | F7: Held flat — prudence
A8: III | B8: Total Income (I+II) | C8: =SUM(C6:C7) | D8: =SUM(D6:D7) | E8: =IFERROR(D8/C8-1,"")
A9: IV | B9: Expenses:
B10: Purchases of Stock-in-Trade | C10: 1.2905596e+08 | D10: =C10*(1+Assumptions!$C$6) | E10: =IFERROR(D10/C10-1,"") | F10: Proportionate +10%
B11: Changes in inventories of finished goods, WIP and stock-in-trade | C11: 26225 | D11: 0 | F11: Taken as NIL — prudence
B12: Employee benefits expense | C12: 4.1438008e+09 | D12: =C12*(1+Assumptions!$C$6) | E12: =IFERROR(D12/C12-1,"") | F12: Proportionate +10%
B13: Finance cost | C13: 34403667 | D13: =C13*(1+Assumptions!$C$6) | E13: =IFERROR(D13/C13-1,"") | F13: +10% — prudence
B14: Depreciation and amortization expense | C14: 26150367 | D14: =C14*(1+Assumptions!$C$6) | E14: =IFERROR(D14/C14-1,"") | F14: +10% — prudence
B15: Other expenses | C15: 4.3367246e+08 | D15: =C15*(1+Assumptions!$C$6) | E15: =IFERROR(D15/C15-1,"") | F15: Proportionate +10%
B16: Total expenses | C16: =SUM(C10:C15) | D16: =SUM(D10:D15) | E16: =D16/C16-1
A17: V | B17: Profit Before Tax (III-IV) | C17: =C8-C16 | D17: =D8-D16 | E17: =D17/C17-1
A18: VI | B18: Tax expense — current tax @ 25.168% | C18: -29662103 | D18: =ROUND(D17*Assumptions!$C$14,0) | E18: =IFERROR(D18/C18-1,"") | F18: Full provision, s.115BAA; FY26 had prior-year tax reversal (credit) — not assumed to recur
A19: VII | B19: Profit After Tax (V-VI) | C19: 1.7078435e+08 | D19: =D17-D18 | E19: =D19/C19-1 | F19: Retained in full — no dividend
B21: PBT margin | C21: =C17/C6 | D21: =D17/D6
B22: PAT margin | C22: =C19/C6 | D22: =D19/D6

Sheet Projected BS FY27
A1: IMPRESSIONS SERVICES PRIVATE LIMITED
A2: PROJECTED BALANCE SHEET AS AT MARCH 31, 2027
A3: CIN: U74930DL2002PTC114966 | Base: BS_TB 2025-26 CONSOLIDATED Set 2 | Amount in INR
B5: Particulars | C5: FY 2025-26 (Base) | D5: FY 2026-27 (Projected) | E5: Change | F5: Basis
A6: I. | B6: EQUITY AND LIABILITIES
A7: (1) | B7: Shareholders’ Funds
A8: (a) | B8: Share capital | C8: 200000 | D8: =C8 | E8: =IFERROR(D8/C8-1,"") | F8: Constant
A9: (b) | B9: Reserves and Surplus | C9: 1.4581152e+09 | D9: =C9+'Projected P&L FY27'!D19 | E9: =IFERROR(D9/C9-1,"") | F9: Opening + projected PAT (nil dividend)
B10: Interunit | C10: 15721314 | D10: =C10 | E10: =IFERROR(D10/C10-1,"") | F10: Held constant
B11: Sub-total — Shareholders’ funds | C11: =SUM(C8:C10) | D11: =SUM(D8:D10)
A12: (2) | B12: Non-current liabilities
A13: (a) | B13: Long-term borrowings | C13: 89963691 | D13: =C13 | E13: =IFERROR(D13/C13-1,"") | F13: Held at FY26 level — prudence
A14: (b) | B14: Long-term provisions (gratuity) | C14: 94505792 | D14: =C14*(1+Assumptions!$C$6) | E14: =IFERROR(D14/C14-1,"") | F14: Grows with employee cost +10%
B15: Sub-total — Non-current liabilities | C15: =SUM(C13:C14) | D15: =SUM(D13:D14)
A16: (3) | B16: Current liabilities
A17: (a) | B17: Short-term borrowings | C17: 3.4813536e+08 | D17: =C17 | E17: =IFERROR(D17/C17-1,"") | F17: Held at FY26 level — prudence
A18: (b) | B18: Trade payables — MSME | C18: 0 | D18: 0
B19: Trade payables — others | C19: 72303716 | D19: =C19*(1+Assumptions!$C$6) | E19: =IFERROR(D19/C19-1,"") | F19: Scales with sales +10%
A20: (c) | B20: Other current liabilities | C20: 4.9550911e+08 | D20: =C20*(1+Assumptions!$C$6) | E20: =IFERROR(D20/C20-1,"") | F20: Scales with sales +10%
A21: (d) | B21: Short-term provisions | C21: 20273487 | D21: =C21*(1+Assumptions!$C$6) | E21: =IFERROR(D21/C21-1,"") | F21: Scales with sales +10%
B22: Sub-total — Current liabilities | C22: =SUM(C17:C21) | D22: =SUM(D17:D21)
B23: TOTAL — EQUITY AND LIABILITIES | C23: =C11+C15+C22 | D23: =D11+D15+D22
A25: II. | B25: ASSETS
A26: (1) | B26: Non-current assets
A27: (a) | B27: Property, plant & equipment (net) | C27: 1.8688091e+08 | D27: =C27 | E27: =IFERROR(D27/C27-1,"") | F27: Capex ≈ depreciation, net block flat
A28: (b) | B28: Non-current investments | C28: 157195317 | D28: =C28 | E28: =IFERROR(D28/C28-1,"") | F28: Held constant
A29: (c) | B29: Deferred tax assets (net) | C29: 29044756 | D29: =C29 | E29: =IFERROR(D29/C29-1,"") | F29: Held constant — prudence (no further DTA built up)
A30: (d) | B30: Long-term loans and advances | C30: 86514245 | D30: =C30 | E30: =IFERROR(D30/C30-1,"") | F30: Held constant
B31: Sub-total — Non-current assets | C31: =SUM(C27:C30) | D31: =SUM(D27:D30)
A32: (2) | B32: Current assets
A33: (a) | B33: Inventories | C33: 4636862 | D33: =C33*(1+Assumptions!$C$6) | E33: =IFERROR(D33/C33-1,"") | F33: Scales with sales +10%
A34: (b) | B34: Trade receivables | C34: 1.6656259e+09 | D34: =C34*(1+Assumptions!$C$6) | E34: =IFERROR(D34/C34-1,"") | F34: Scales with sales +10% (same collection cycle)
A35: (c) | B35: Short-term loans and advances | C35: 393603021 | D35: =C35*(1+Assumptions!$C$6) | E35: =IFERROR(D35/C35-1,"") | F35: Scales with sales +10%
A36: (d) | B36: Other current assets | C36: 23144281 | D36: =C36*(1+Assumptions!$C$6) | E36: =IFERROR(D36/C36-1,"") | F36: Scales with sales +10%
A37: (e) | B37: Cash and cash equivalents | C37: 48082440 | D37: =D23-SUM(D27:D30)-SUM(D33:D36) | E37: =D37/C37-1 | F37: Balancing figure
B38: Sub-total — Current assets | C38: =SUM(C33:C37) | D38: =SUM(D33:D37)
B39: TOTAL — ASSETS | C39: =C31+C38 | D39: =D31+D38
B41: Check: Total assets less total equity & liabilities | D41: =D39-D23

Sheet Summary & Ratios
A1: IMPRESSIONS SERVICES PRIVATE LIMITED
A2: PROJECTION SUMMARY — FY 2026-27 vs FY 2025-26 (₹ Crore)
A3: CIN: U74930DL2002PTC114966 | Base: BS_TB 2025-26 CONSOLIDATED Set 2 | Amount in INR
A5: Metric | B5: FY 2025-26 | C5: FY 2026-27 (Proj) | D5: Change
A6: Revenue from operations | B6: ='Projected P&L FY27'!C6 | C6: ='Projected P&L FY27'!D6 | D6: =IFERROR(C6/B6-1,"")
A7: Total expenses | B7: ='Projected P&L FY27'!C16 | C7: ='Projected P&L FY27'!D16 | D7: =IFERROR(C7/B7-1,"")
A8: Profit before tax | B8: ='Projected P&L FY27'!C17 | C8: ='Projected P&L FY27'!D17 | D8: =IFERROR(C8/B8-1,"")
A9: Profit after tax | B9: ='Projected P&L FY27'!C19 | C9: ='Projected P&L FY27'!D19 | D9: =IFERROR(C9/B9-1,"")
A10: Net worth (incl. interunit) | B10: ='Projected BS FY27'!C11 | C10: ='Projected BS FY27'!D11 | D10: =IFERROR(C10/B10-1,"")
A11: Total borrowings (LT+ST) | B11: ='Projected BS FY27'!C13+'Projected BS FY27'!C17 | C11: ='Projected BS FY27'!D13+'Projected BS FY27'!D17 | D11: =IFERROR(C11/B11-1,"")
A12: Trade receivables | B12: ='Projected BS FY27'!C34 | C12: ='Projected BS FY27'!D34 | D12: =IFERROR(C12/B12-1,"")
A13: Cash & cash equivalents | B13: ='Projected BS FY27'!C37 | C13: ='Projected BS FY27'!D37 | D13: =IFERROR(C13/B13-1,"")
A14: Balance sheet total | B14: ='Projected BS FY27'!C39 | C14: ='Projected BS FY27'!D39 | D14: =IFERROR(C14/B14-1,"")
A15: Working capital (CA − CL) | B15: ='Projected BS FY27'!C38-'Projected BS FY27'!C22 | C15: ='Projected BS FY27'!D38-'Projected BS FY27'!D22 | D15: =IFERROR(C15/B15-1,"")
A17: Key ratios
A18: PBT margin % | B18: ='Projected P&L FY27'!C17/'Projected P&L FY27'!C6*100 | C18: ='Projected P&L FY27'!D17/'Projected P&L FY27'!D6*100 | D18: =C18-B18
A19: PAT margin % | B19: ='Projected P&L FY27'!C19/'Projected P&L FY27'!C6*100 | C19: ='Projected P&L FY27'!D19/'Projected P&L FY27'!D6*100 | D19: =C19-B19
A20: Current ratio (x) | B20: ='Projected BS FY27'!C38/'Projected BS FY27'!C22 | C20: ='Projected BS FY27'!D38/'Projected BS FY27'!D22 | D20: =C20-B20
A21: Debt / equity (x) | B21: =('Projected BS FY27'!C13+'Projected BS FY27'!C17)/'Projected BS FY27'!C11 | C21: =('Projected BS FY27'!D13+'Projected BS FY27'!D17)/'Projected BS FY27'!D11 | D21: =C21-B21
A22: Debtor days (on closing TR) | B22: ='Projected BS FY27'!C34/'Projected P&L FY27'!C6*365 | C22: ='Projected BS FY27'!D34/'Projected P&L FY27'!D6*365 | D22: =C22-B22
A23: Return on net worth % | B23: ='Projected P&L FY27'!C19/'Projected BS FY27'!C11*100 | C23: ='Projected P&L FY27'!D19/'Projected BS FY27'!D11*100 | D23: =C23-B23
A25: Prudence notes:
A26: 1. Other income NOT grown — held at FY 2025-26 level.
A27: 2. FY 2025-26 PAT (₹17.08 Cr) includes a prior-year current-tax reversal of ₹2.97 Cr; the projection assumes NO such credit and provides full tax at 25.168%, so projected PAT growth appears muted vs the reported base.
A28: 3. Inventory change taken as nil; no stock-appreciation gain assumed.
A29: 4. Borrowings held at FY26 levels — incremental working capital is funded from internal accruals; cash is the balancing figure.
A30: 5. Entire PAT retained; no dividend assumed.
A31: 6. Gratuity (long-term provision) grown in line with employee cost.
